{
  "config": {
    "rodadaAtual": 5,
    "pontos": {
      "pergunta": {
        "proporcaoPerda": 0.5,
        "facil": 250,
        "medio": 500,
        "dificil": 1000,
        "final": 5000
      },
      "musica": {
        "proporcaoPerda": 0.5,
        "padrao": 2000
      }
    }
  },
  "rodadas": {
    "-1": {
      "andamento": {
        "etapaAtual": "perguntas",
        "jogadorAtual": "jogador1",
        "faseAtual": 1,
        "sequencia": []
      },
      "finalizada": false,
      "numeroRodada": 5,
      "jogadores": {
        "jogador1": {
          "nome": "",
          "pontos": 0,
          "id": "jogador1"
        },
        "jogador2": {
          "nome": "",
          "pontos": 0,
          "id": "jogador2"
        }
      },
      "perguntas": {
        "jogador1": {
          "1":{
            "enunciado": "TEXTO QUESTÃO 1",
            "dificuldade": "facil",
            "opcoes": {
              "a": {
                "texto": "TEXTO ALTERNATIVA A",
                "correta": false
              },
              "b": {
                "texto": "TEXTO ALTERNATIVA B",
                "correta": true
              },
              "c": {
                "texto": "TEXTO ALTERNATIVA C",
                "correta": false
              },
              "d": {
                "texto": "TEXTO ALTERNATIVA D",
                "correta": false
              }
            }
          },
          "2":{
            "enunciado": "TEXTO QUESTÃO 1",
            "dificuldade": "facil",
            "opcoes": {
              "a": {
                "texto": "TEXTO ALTERNATIVA A",
                "correta": false
              },
              "b": {
                "texto": "TEXTO ALTERNATIVA B",
                "correta": true
              },
              "c": {
                "texto": "TEXTO ALTERNATIVA C",
                "correta": false
              },
              "d": {
                "texto": "TEXTO ALTERNATIVA D",
                "correta": false
              }
            }
          },
          "3":{
            "enunciado": "TEXTO QUESTÃO 1",
            "dificuldade": "facil",
            "opcoes": {
              "a": {
                "texto": "TEXTO ALTERNATIVA A",
                "correta": false
              },
              "b": {
                "texto": "TEXTO ALTERNATIVA B",
                "correta": true
              },
              "c": {
                "texto": "TEXTO ALTERNATIVA C",
                "correta": false
              },
              "d": {
                "texto": "TEXTO ALTERNATIVA D",
                "correta": false
              }
            }
          },
          "4":{
            "enunciado": "TEXTO QUESTÃO 1",
            "dificuldade": "facil",
            "opcoes": {
              "a": {
                "texto": "TEXTO ALTERNATIVA A",
                "correta": false
              },
              "b": {
                "texto": "TEXTO ALTERNATIVA B",
                "correta": true
              },
              "c": {
                "texto": "TEXTO ALTERNATIVA C",
                "correta": false
              },
              "d": {
                "texto": "TEXTO ALTERNATIVA D",
                "correta": false
              }
            }
          },
          "5":{
            "enunciado": "TEXTO QUESTÃO 1",
            "dificuldade": "facil",
            "opcoes": {
              "a": {
                "texto": "TEXTO ALTERNATIVA A",
                "correta": false
              },
              "b": {
                "texto": "TEXTO ALTERNATIVA B",
                "correta": true
              },
              "c": {
                "texto": "TEXTO ALTERNATIVA C",
                "correta": false
              },
              "d": {
                "texto": "TEXTO ALTERNATIVA D",
                "correta": false
              }
            }
          },
          "6":{
            "enunciado": "TEXTO QUESTÃO 1",
            "dificuldade": "facil",
            "opcoes": {
              "a": {
                "texto": "TEXTO ALTERNATIVA A",
                "correta": false
              },
              "b": {
                "texto": "TEXTO ALTERNATIVA B",
                "correta": true
              },
              "c": {
                "texto": "TEXTO ALTERNATIVA C",
                "correta": false
              },
              "d": {
                "texto": "TEXTO ALTERNATIVA D",
                "correta": false
              }
            }
          },
          "7":{
            "enunciado": "TEXTO QUESTÃO 1",
            "dificuldade": "facil",
            "opcoes": {
              "a": {
                "texto": "TEXTO ALTERNATIVA A",
                "correta": false
              },
              "b": {
                "texto": "TEXTO ALTERNATIVA B",
                "correta": true
              },
              "c": {
                "texto": "TEXTO ALTERNATIVA C",
                "correta": false
              },
              "d": {
                "texto": "TEXTO ALTERNATIVA D",
                "correta": false
              }
            }
          },
          "8":{
            "enunciado": "TEXTO QUESTÃO 1",
            "dificuldade": "facil",
            "opcoes": {
              "a": {
                "texto": "TEXTO ALTERNATIVA A",
                "correta": false
              },
              "b": {
                "texto": "TEXTO ALTERNATIVA B",
                "correta": true
              },
              "c": {
                "texto": "TEXTO ALTERNATIVA C",
                "correta": false
              },
              "d": {
                "texto": "TEXTO ALTERNATIVA D",
                "correta": false
              }
            }
          },
          "9":{
            "enunciado": "TEXTO QUESTÃO 1",
            "dificuldade": "facil",
            "opcoes": {
              "a": {
                "texto": "TEXTO ALTERNATIVA A",
                "correta": false
              },
              "b": {
                "texto": "TEXTO ALTERNATIVA B",
                "correta": true
              },
              "c": {
                "texto": "TEXTO ALTERNATIVA C",
                "correta": false
              },
              "d": {
                "texto": "TEXTO ALTERNATIVA D",
                "correta": false
              }
            }
          },
          "10":{
            "enunciado": "TEXTO QUESTÃO 1",
            "dificuldade": "facil",
            "opcoes": {
              "a": {
                "texto": "TEXTO ALTERNATIVA A",
                "correta": false
              },
              "b": {
                "texto": "TEXTO ALTERNATIVA B",
                "correta": true
              },
              "c": {
                "texto": "TEXTO ALTERNATIVA C",
                "correta": false
              },
              "d": {
                "texto": "TEXTO ALTERNATIVA D",
                "correta": false
              }
            }
          },
          "11":{
            "enunciado": "TEXTO QUESTÃO 1",
            "dificuldade": "facil",
            "opcoes": {
              "a": {
                "texto": "TEXTO ALTERNATIVA A",
                "correta": false
              },
              "b": {
                "texto": "TEXTO ALTERNATIVA B",
                "correta": true
              },
              "c": {
                "texto": "TEXTO ALTERNATIVA C",
                "correta": false
              },
              "d": {
                "texto": "TEXTO ALTERNATIVA D",
                "correta": false
              }
            }
          },
          "12":{
            "enunciado": "TEXTO QUESTÃO 1",
            "dificuldade": "facil",
            "opcoes": {
              "a": {
                "texto": "TEXTO ALTERNATIVA A",
                "correta": false
              },
              "b": {
                "texto": "TEXTO ALTERNATIVA B",
                "correta": true
              },
              "c": {
                "texto": "TEXTO ALTERNATIVA C",
                "correta": false
              },
              "d": {
                "texto": "TEXTO ALTERNATIVA D",
                "correta": false
              }
            }
          },
          "13":{
            "enunciado": "TEXTO QUESTÃO 1",
            "dificuldade": "facil",
            "opcoes": {
              "a": {
                "texto": "TEXTO ALTERNATIVA A",
                "correta": false
              },
              "b": {
                "texto": "TEXTO ALTERNATIVA B",
                "correta": true
              },
              "c": {
                "texto": "TEXTO ALTERNATIVA C",
                "correta": false
              },
              "d": {
                "texto": "TEXTO ALTERNATIVA D",
                "correta": false
              }
            }
          },
          "14":{
            "enunciado": "TEXTO QUESTÃO 1",
            "dificuldade": "facil",
            "opcoes": {
              "a": {
                "texto": "TEXTO ALTERNATIVA A",
                "correta": false
              },
              "b": {
                "texto": "TEXTO ALTERNATIVA B",
                "correta": true
              },
              "c": {
                "texto": "TEXTO ALTERNATIVA C",
                "correta": false
              },
              "d": {
                "texto": "TEXTO ALTERNATIVA D",
                "correta": false
              }
            }
          },
          "15":{
            "enunciado": "TEXTO QUESTÃO 1",
            "dificuldade": "facil",
            "opcoes": {
              "a": {
                "texto": "TEXTO ALTERNATIVA A",
                "correta": false
              },
              "b": {
                "texto": "TEXTO ALTERNATIVA B",
                "correta": true
              },
              "c": {
                "texto": "TEXTO ALTERNATIVA C",
                "correta": false
              },
              "d": {
                "texto": "TEXTO ALTERNATIVA D",
                "correta": false
              }
            }
          }
        },
        "jogador2": {
          "1":{
            "enunciado": "TEXTO QUESTÃO",
            "dificuldade": "facil",
            "opcoes": {
              "a": {
                "texto": "TEXTO ALTERNATIVA A",
                "correta": true
              },
              "b": {
                "texto": "TEXTO ALTERNATIVA B",
                "correta": false
              },
              "c": {
                "texto": "TEXTO ALTERNATIVA C",
                "correta": false
              },
              "d": {
                "texto": "TEXTO ALTERNATIVA D",
                "correta": false
              }
            }
          },
          "2":{
            "enunciado": "TEXTO QUESTÃO",
            "dificuldade": "facil",
            "opcoes": {
              "a": {
                "texto": "TEXTO ALTERNATIVA A",
                "correta": true
              },
              "b": {
                "texto": "TEXTO ALTERNATIVA B",
                "correta": false
              },
              "c": {
                "texto": "TEXTO ALTERNATIVA C",
                "correta": false
              },
              "d": {
                "texto": "TEXTO ALTERNATIVA D",
                "correta": false
              }
            }
          },
          "3":{
            "enunciado": "TEXTO QUESTÃO",
            "dificuldade": "facil",
            "opcoes": {
              "a": {
                "texto": "TEXTO ALTERNATIVA A",
                "correta": true
              },
              "b": {
                "texto": "TEXTO ALTERNATIVA B",
                "correta": false
              },
              "c": {
                "texto": "TEXTO ALTERNATIVA C",
                "correta": false
              },
              "d": {
                "texto": "TEXTO ALTERNATIVA D",
                "correta": false
              }
            }
          },
          "4":{
            "enunciado": "TEXTO QUESTÃO",
            "dificuldade": "facil",
            "opcoes": {
              "a": {
                "texto": "TEXTO ALTERNATIVA A",
                "correta": true
              },
              "b": {
                "texto": "TEXTO ALTERNATIVA B",
                "correta": false
              },
              "c": {
                "texto": "TEXTO ALTERNATIVA C",
                "correta": false
              },
              "d": {
                "texto": "TEXTO ALTERNATIVA D",
                "correta": false
              }
            }
          },
          "5":{
            "enunciado": "TEXTO QUESTÃO",
            "dificuldade": "facil",
            "opcoes": {
              "a": {
                "texto": "TEXTO ALTERNATIVA A",
                "correta": true
              },
              "b": {
                "texto": "TEXTO ALTERNATIVA B",
                "correta": false
              },
              "c": {
                "texto": "TEXTO ALTERNATIVA C",
                "correta": false
              },
              "d": {
                "texto": "TEXTO ALTERNATIVA D",
                "correta": false
              }
            }
          },
          "6":{
            "enunciado": "TEXTO QUESTÃO",
            "dificuldade": "facil",
            "opcoes": {
              "a": {
                "texto": "TEXTO ALTERNATIVA A",
                "correta": true
              },
              "b": {
                "texto": "TEXTO ALTERNATIVA B",
                "correta": false
              },
              "c": {
                "texto": "TEXTO ALTERNATIVA C",
                "correta": false
              },
              "d": {
                "texto": "TEXTO ALTERNATIVA D",
                "correta": false
              }
            }
          },
          "7":{
            "enunciado": "TEXTO QUESTÃO",
            "dificuldade": "facil",
            "opcoes": {
              "a": {
                "texto": "TEXTO ALTERNATIVA A",
                "correta": true
              },
              "b": {
                "texto": "TEXTO ALTERNATIVA B",
                "correta": false
              },
              "c": {
                "texto": "TEXTO ALTERNATIVA C",
                "correta": false
              },
              "d": {
                "texto": "TEXTO ALTERNATIVA D",
                "correta": false
              }
            }
          },
          "8":{
            "enunciado": "TEXTO QUESTÃO",
            "dificuldade": "facil",
            "opcoes": {
              "a": {
                "texto": "TEXTO ALTERNATIVA A",
                "correta": true
              },
              "b": {
                "texto": "TEXTO ALTERNATIVA B",
                "correta": false
              },
              "c": {
                "texto": "TEXTO ALTERNATIVA C",
                "correta": false
              },
              "d": {
                "texto": "TEXTO ALTERNATIVA D",
                "correta": false
              }
            }
          },
          "9":{
            "enunciado": "TEXTO QUESTÃO",
            "dificuldade": "facil",
            "opcoes": {
              "a": {
                "texto": "TEXTO ALTERNATIVA A",
                "correta": true
              },
              "b": {
                "texto": "TEXTO ALTERNATIVA B",
                "correta": false
              },
              "c": {
                "texto": "TEXTO ALTERNATIVA C",
                "correta": false
              },
              "d": {
                "texto": "TEXTO ALTERNATIVA D",
                "correta": false
              }
            }
          },
          "10":{
            "enunciado": "TEXTO QUESTÃO",
            "dificuldade": "facil",
            "opcoes": {
              "a": {
                "texto": "TEXTO ALTERNATIVA A",
                "correta": true
              },
              "b": {
                "texto": "TEXTO ALTERNATIVA B",
                "correta": false
              },
              "c": {
                "texto": "TEXTO ALTERNATIVA C",
                "correta": false
              },
              "d": {
                "texto": "TEXTO ALTERNATIVA D",
                "correta": false
              }
            }
          },
          "11":{
            "enunciado": "TEXTO QUESTÃO",
            "dificuldade": "facil",
            "opcoes": {
              "a": {
                "texto": "TEXTO ALTERNATIVA A",
                "correta": true
              },
              "b": {
                "texto": "TEXTO ALTERNATIVA B",
                "correta": false
              },
              "c": {
                "texto": "TEXTO ALTERNATIVA C",
                "correta": false
              },
              "d": {
                "texto": "TEXTO ALTERNATIVA D",
                "correta": false
              }
            }
          },
          "12":{
            "enunciado": "TEXTO QUESTÃO",
            "dificuldade": "facil",
            "opcoes": {
              "a": {
                "texto": "TEXTO ALTERNATIVA A",
                "correta": true
              },
              "b": {
                "texto": "TEXTO ALTERNATIVA B",
                "correta": false
              },
              "c": {
                "texto": "TEXTO ALTERNATIVA C",
                "correta": false
              },
              "d": {
                "texto": "TEXTO ALTERNATIVA D",
                "correta": false
              }
            }
          },
          "13":{
            "enunciado": "TEXTO QUESTÃO",
            "dificuldade": "facil",
            "opcoes": {
              "a": {
                "texto": "TEXTO ALTERNATIVA A",
                "correta": true
              },
              "b": {
                "texto": "TEXTO ALTERNATIVA B",
                "correta": false
              },
              "c": {
                "texto": "TEXTO ALTERNATIVA C",
                "correta": false
              },
              "d": {
                "texto": "TEXTO ALTERNATIVA D",
                "correta": false
              }
            }
          },
          "14":{
            "enunciado": "TEXTO QUESTÃO",
            "dificuldade": "facil",
            "opcoes": {
              "a": {
                "texto": "TEXTO ALTERNATIVA A",
                "correta": true
              },
              "b": {
                "texto": "TEXTO ALTERNATIVA B",
                "correta": false
              },
              "c": {
                "texto": "TEXTO ALTERNATIVA C",
                "correta": false
              },
              "d": {
                "texto": "TEXTO ALTERNATIVA D",
                "correta": false
              }
            }
          },
          "15":{
            "enunciado": "TEXTO QUESTÃO",
            "dificuldade": "facil",
            "opcoes": {
              "a": {
                "texto": "TEXTO ALTERNATIVA A",
                "correta": true
              },
              "b": {
                "texto": "TEXTO ALTERNATIVA B",
                "correta": false
              },
              "c": {
                "texto": "TEXTO ALTERNATIVA C",
                "correta": false
              },
              "d": {
                "texto": "TEXTO ALTERNATIVA D",
                "correta": false
              }
            }
          }
        }
      },
      "musicas": {
        "1": {
          "nomeMusica": "Nome da Música",
          "url": "link da música"
        },
        "2": {
          "nomeMusica": "Nome da Música",
          "url": "link da música"
        },
        "3": {
          "nomeMusica": "Nome da Música",
          "url": "link da música"
        },
        "4": {
          "nomeMusica": "Nome da Música",
          "url": "link da música"
        },
        "5": {
          "nomeMusica": "Nome da Música",
          "url": "link da música"
        },
        "6": {
          "nomeMusica": "Nome da Música",
          "url": "link da música"
        },
        "7": {
          "nomeMusica": "Nome da Música",
          "url": "link da música"
        },
        "8": {
          "nomeMusica": "Nome da Música",
          "url": "link da música"
        },
        "9": {
          "nomeMusica": "Nome da Música",
          "url": "link da música"
        },
        "10": {
          "nomeMusica": "Nome da Música",
          "url": "link da música"
        },
        "11": {
          "nomeMusica": "Nome da Música",
          "url": "link da música"
        },
        "12": {
          "nomeMusica": "Nome da Música",
          "url": "link da música"
        }
      },
      "frases": {
        "jogador1": {
          "1": {
          },
          "2": {
          },
          "3": {
          }
        },
        "jogador2": {
          "1": {
          },
          "2": {
          },
          "3": {
          }
        }
      }
    },
    "5": {
      "andamento": {
        "etapaAtual": "perguntas",
        "jogadorAtual": "jogador1",
        "faseAtual": 1,
        "sequencia": []
      },
      "finalizada": false,
      "numeroRodada": 5,
      "jogadores": {
        "jogador1": {
          "nome": "",
          "pontos": 0,
          "id": "jogador1"
        },
        "jogador2": {
          "nome": "",
          "pontos": 0,
          "id": "jogador2"
        }
      },
      "perguntas": {
        "jogador1": {
          "1":{
            "enunciado": "TEXTO QUESTÃO 1",
            "dificuldade": "facil",
            "opcoes": {
              "a": {
                "texto": "TEXTO ALTERNATIVA A",
                "correta": false
              },
              "b": {
                "texto": "TEXTO ALTERNATIVA B",
                "correta": true
              },
              "c": {
                "texto": "TEXTO ALTERNATIVA C",
                "correta": false
              },
              "d": {
                "texto": "TEXTO ALTERNATIVA D",
                "correta": false
              }
            }
          },
          "2":{
            "enunciado": "TEXTO QUESTÃO 1",
            "dificuldade": "facil",
            "opcoes": {
              "a": {
                "texto": "TEXTO ALTERNATIVA A",
                "correta": false
              },
              "b": {
                "texto": "TEXTO ALTERNATIVA B",
                "correta": true
              },
              "c": {
                "texto": "TEXTO ALTERNATIVA C",
                "correta": false
              },
              "d": {
                "texto": "TEXTO ALTERNATIVA D",
                "correta": false
              }
            }
          },
          "3":{
            "enunciado": "TEXTO QUESTÃO 1",
            "dificuldade": "facil",
            "opcoes": {
              "a": {
                "texto": "TEXTO ALTERNATIVA A",
                "correta": false
              },
              "b": {
                "texto": "TEXTO ALTERNATIVA B",
                "correta": true
              },
              "c": {
                "texto": "TEXTO ALTERNATIVA C",
                "correta": false
              },
              "d": {
                "texto": "TEXTO ALTERNATIVA D",
                "correta": false
              }
            }
          },
          "4":{
            "enunciado": "TEXTO QUESTÃO 1",
            "dificuldade": "facil",
            "opcoes": {
              "a": {
                "texto": "TEXTO ALTERNATIVA A",
                "correta": false
              },
              "b": {
                "texto": "TEXTO ALTERNATIVA B",
                "correta": true
              },
              "c": {
                "texto": "TEXTO ALTERNATIVA C",
                "correta": false
              },
              "d": {
                "texto": "TEXTO ALTERNATIVA D",
                "correta": false
              }
            }
          },
          "5":{
            "enunciado": "TEXTO QUESTÃO 1",
            "dificuldade": "facil",
            "opcoes": {
              "a": {
                "texto": "TEXTO ALTERNATIVA A",
                "correta": false
              },
              "b": {
                "texto": "TEXTO ALTERNATIVA B",
                "correta": true
              },
              "c": {
                "texto": "TEXTO ALTERNATIVA C",
                "correta": false
              },
              "d": {
                "texto": "TEXTO ALTERNATIVA D",
                "correta": false
              }
            }
          },
          "6":{
            "enunciado": "TEXTO QUESTÃO 1",
            "dificuldade": "facil",
            "opcoes": {
              "a": {
                "texto": "TEXTO ALTERNATIVA A",
                "correta": false
              },
              "b": {
                "texto": "TEXTO ALTERNATIVA B",
                "correta": true
              },
              "c": {
                "texto": "TEXTO ALTERNATIVA C",
                "correta": false
              },
              "d": {
                "texto": "TEXTO ALTERNATIVA D",
                "correta": false
              }
            }
          },
          "7":{
            "enunciado": "TEXTO QUESTÃO 1",
            "dificuldade": "facil",
            "opcoes": {
              "a": {
                "texto": "TEXTO ALTERNATIVA A",
                "correta": false
              },
              "b": {
                "texto": "TEXTO ALTERNATIVA B",
                "correta": true
              },
              "c": {
                "texto": "TEXTO ALTERNATIVA C",
                "correta": false
              },
              "d": {
                "texto": "TEXTO ALTERNATIVA D",
                "correta": false
              }
            }
          },
          "8":{
            "enunciado": "TEXTO QUESTÃO 1",
            "dificuldade": "facil",
            "opcoes": {
              "a": {
                "texto": "TEXTO ALTERNATIVA A",
                "correta": false
              },
              "b": {
                "texto": "TEXTO ALTERNATIVA B",
                "correta": true
              },
              "c": {
                "texto": "TEXTO ALTERNATIVA C",
                "correta": false
              },
              "d": {
                "texto": "TEXTO ALTERNATIVA D",
                "correta": false
              }
            }
          },
          "9":{
            "enunciado": "TEXTO QUESTÃO 1",
            "dificuldade": "facil",
            "opcoes": {
              "a": {
                "texto": "TEXTO ALTERNATIVA A",
                "correta": false
              },
              "b": {
                "texto": "TEXTO ALTERNATIVA B",
                "correta": true
              },
              "c": {
                "texto": "TEXTO ALTERNATIVA C",
                "correta": false
              },
              "d": {
                "texto": "TEXTO ALTERNATIVA D",
                "correta": false
              }
            }
          },
          "10":{
            "enunciado": "TEXTO QUESTÃO 1",
            "dificuldade": "facil",
            "opcoes": {
              "a": {
                "texto": "TEXTO ALTERNATIVA A",
                "correta": false
              },
              "b": {
                "texto": "TEXTO ALTERNATIVA B",
                "correta": true
              },
              "c": {
                "texto": "TEXTO ALTERNATIVA C",
                "correta": false
              },
              "d": {
                "texto": "TEXTO ALTERNATIVA D",
                "correta": false
              }
            }
          },
          "11":{
            "enunciado": "TEXTO QUESTÃO 1",
            "dificuldade": "facil",
            "opcoes": {
              "a": {
                "texto": "TEXTO ALTERNATIVA A",
                "correta": false
              },
              "b": {
                "texto": "TEXTO ALTERNATIVA B",
                "correta": true
              },
              "c": {
                "texto": "TEXTO ALTERNATIVA C",
                "correta": false
              },
              "d": {
                "texto": "TEXTO ALTERNATIVA D",
                "correta": false
              }
            }
          },
          "12":{
            "enunciado": "TEXTO QUESTÃO 1",
            "dificuldade": "facil",
            "opcoes": {
              "a": {
                "texto": "TEXTO ALTERNATIVA A",
                "correta": false
              },
              "b": {
                "texto": "TEXTO ALTERNATIVA B",
                "correta": true
              },
              "c": {
                "texto": "TEXTO ALTERNATIVA C",
                "correta": false
              },
              "d": {
                "texto": "TEXTO ALTERNATIVA D",
                "correta": false
              }
            }
          },
          "13":{
            "enunciado": "TEXTO QUESTÃO 1",
            "dificuldade": "facil",
            "opcoes": {
              "a": {
                "texto": "TEXTO ALTERNATIVA A",
                "correta": false
              },
              "b": {
                "texto": "TEXTO ALTERNATIVA B",
                "correta": true
              },
              "c": {
                "texto": "TEXTO ALTERNATIVA C",
                "correta": false
              },
              "d": {
                "texto": "TEXTO ALTERNATIVA D",
                "correta": false
              }
            }
          },
          "14":{
            "enunciado": "TEXTO QUESTÃO 1",
            "dificuldade": "facil",
            "opcoes": {
              "a": {
                "texto": "TEXTO ALTERNATIVA A",
                "correta": false
              },
              "b": {
                "texto": "TEXTO ALTERNATIVA B",
                "correta": true
              },
              "c": {
                "texto": "TEXTO ALTERNATIVA C",
                "correta": false
              },
              "d": {
                "texto": "TEXTO ALTERNATIVA D",
                "correta": false
              }
            }
          },
          "15":{
            "enunciado": "TEXTO QUESTÃO 1",
            "dificuldade": "facil",
            "opcoes": {
              "a": {
                "texto": "TEXTO ALTERNATIVA A",
                "correta": false
              },
              "b": {
                "texto": "TEXTO ALTERNATIVA B",
                "correta": true
              },
              "c": {
                "texto": "TEXTO ALTERNATIVA C",
                "correta": false
              },
              "d": {
                "texto": "TEXTO ALTERNATIVA D",
                "correta": false
              }
            }
          }
        },
        "jogador2": {
          "1":{
            "enunciado": "TEXTO QUESTÃO",
            "dificuldade": "facil",
            "opcoes": {
              "a": {
                "texto": "TEXTO ALTERNATIVA A",
                "correta": true
              },
              "b": {
                "texto": "TEXTO ALTERNATIVA B",
                "correta": false
              },
              "c": {
                "texto": "TEXTO ALTERNATIVA C",
                "correta": false
              },
              "d": {
                "texto": "TEXTO ALTERNATIVA D",
                "correta": false
              }
            }
          },
          "2":{
            "enunciado": "TEXTO QUESTÃO",
            "dificuldade": "facil",
            "opcoes": {
              "a": {
                "texto": "TEXTO ALTERNATIVA A",
                "correta": true
              },
              "b": {
                "texto": "TEXTO ALTERNATIVA B",
                "correta": false
              },
              "c": {
                "texto": "TEXTO ALTERNATIVA C",
                "correta": false
              },
              "d": {
                "texto": "TEXTO ALTERNATIVA D",
                "correta": false
              }
            }
          },
          "3":{
            "enunciado": "TEXTO QUESTÃO",
            "dificuldade": "facil",
            "opcoes": {
              "a": {
                "texto": "TEXTO ALTERNATIVA A",
                "correta": true
              },
              "b": {
                "texto": "TEXTO ALTERNATIVA B",
                "correta": false
              },
              "c": {
                "texto": "TEXTO ALTERNATIVA C",
                "correta": false
              },
              "d": {
                "texto": "TEXTO ALTERNATIVA D",
                "correta": false
              }
            }
          },
          "4":{
            "enunciado": "TEXTO QUESTÃO",
            "dificuldade": "facil",
            "opcoes": {
              "a": {
                "texto": "TEXTO ALTERNATIVA A",
                "correta": true
              },
              "b": {
                "texto": "TEXTO ALTERNATIVA B",
                "correta": false
              },
              "c": {
                "texto": "TEXTO ALTERNATIVA C",
                "correta": false
              },
              "d": {
                "texto": "TEXTO ALTERNATIVA D",
                "correta": false
              }
            }
          },
          "5":{
            "enunciado": "TEXTO QUESTÃO",
            "dificuldade": "facil",
            "opcoes": {
              "a": {
                "texto": "TEXTO ALTERNATIVA A",
                "correta": true
              },
              "b": {
                "texto": "TEXTO ALTERNATIVA B",
                "correta": false
              },
              "c": {
                "texto": "TEXTO ALTERNATIVA C",
                "correta": false
              },
              "d": {
                "texto": "TEXTO ALTERNATIVA D",
                "correta": false
              }
            }
          },
          "6":{
            "enunciado": "TEXTO QUESTÃO",
            "dificuldade": "facil",
            "opcoes": {
              "a": {
                "texto": "TEXTO ALTERNATIVA A",
                "correta": true
              },
              "b": {
                "texto": "TEXTO ALTERNATIVA B",
                "correta": false
              },
              "c": {
                "texto": "TEXTO ALTERNATIVA C",
                "correta": false
              },
              "d": {
                "texto": "TEXTO ALTERNATIVA D",
                "correta": false
              }
            }
          },
          "7":{
            "enunciado": "TEXTO QUESTÃO",
            "dificuldade": "facil",
            "opcoes": {
              "a": {
                "texto": "TEXTO ALTERNATIVA A",
                "correta": true
              },
              "b": {
                "texto": "TEXTO ALTERNATIVA B",
                "correta": false
              },
              "c": {
                "texto": "TEXTO ALTERNATIVA C",
                "correta": false
              },
              "d": {
                "texto": "TEXTO ALTERNATIVA D",
                "correta": false
              }
            }
          },
          "8":{
            "enunciado": "TEXTO QUESTÃO",
            "dificuldade": "facil",
            "opcoes": {
              "a": {
                "texto": "TEXTO ALTERNATIVA A",
                "correta": true
              },
              "b": {
                "texto": "TEXTO ALTERNATIVA B",
                "correta": false
              },
              "c": {
                "texto": "TEXTO ALTERNATIVA C",
                "correta": false
              },
              "d": {
                "texto": "TEXTO ALTERNATIVA D",
                "correta": false
              }
            }
          },
          "9":{
            "enunciado": "TEXTO QUESTÃO",
            "dificuldade": "facil",
            "opcoes": {
              "a": {
                "texto": "TEXTO ALTERNATIVA A",
                "correta": true
              },
              "b": {
                "texto": "TEXTO ALTERNATIVA B",
                "correta": false
              },
              "c": {
                "texto": "TEXTO ALTERNATIVA C",
                "correta": false
              },
              "d": {
                "texto": "TEXTO ALTERNATIVA D",
                "correta": false
              }
            }
          },
          "10":{
            "enunciado": "TEXTO QUESTÃO",
            "dificuldade": "facil",
            "opcoes": {
              "a": {
                "texto": "TEXTO ALTERNATIVA A",
                "correta": true
              },
              "b": {
                "texto": "TEXTO ALTERNATIVA B",
                "correta": false
              },
              "c": {
                "texto": "TEXTO ALTERNATIVA C",
                "correta": false
              },
              "d": {
                "texto": "TEXTO ALTERNATIVA D",
                "correta": false
              }
            }
          },
          "11":{
            "enunciado": "TEXTO QUESTÃO",
            "dificuldade": "facil",
            "opcoes": {
              "a": {
                "texto": "TEXTO ALTERNATIVA A",
                "correta": true
              },
              "b": {
                "texto": "TEXTO ALTERNATIVA B",
                "correta": false
              },
              "c": {
                "texto": "TEXTO ALTERNATIVA C",
                "correta": false
              },
              "d": {
                "texto": "TEXTO ALTERNATIVA D",
                "correta": false
              }
            }
          },
          "12":{
            "enunciado": "TEXTO QUESTÃO",
            "dificuldade": "facil",
            "opcoes": {
              "a": {
                "texto": "TEXTO ALTERNATIVA A",
                "correta": true
              },
              "b": {
                "texto": "TEXTO ALTERNATIVA B",
                "correta": false
              },
              "c": {
                "texto": "TEXTO ALTERNATIVA C",
                "correta": false
              },
              "d": {
                "texto": "TEXTO ALTERNATIVA D",
                "correta": false
              }
            }
          },
          "13":{
            "enunciado": "TEXTO QUESTÃO",
            "dificuldade": "facil",
            "opcoes": {
              "a": {
                "texto": "TEXTO ALTERNATIVA A",
                "correta": true
              },
              "b": {
                "texto": "TEXTO ALTERNATIVA B",
                "correta": false
              },
              "c": {
                "texto": "TEXTO ALTERNATIVA C",
                "correta": false
              },
              "d": {
                "texto": "TEXTO ALTERNATIVA D",
                "correta": false
              }
            }
          },
          "14":{
            "enunciado": "TEXTO QUESTÃO",
            "dificuldade": "facil",
            "opcoes": {
              "a": {
                "texto": "TEXTO ALTERNATIVA A",
                "correta": true
              },
              "b": {
                "texto": "TEXTO ALTERNATIVA B",
                "correta": false
              },
              "c": {
                "texto": "TEXTO ALTERNATIVA C",
                "correta": false
              },
              "d": {
                "texto": "TEXTO ALTERNATIVA D",
                "correta": false
              }
            }
          },
          "15":{
            "enunciado": "TEXTO QUESTÃO",
            "dificuldade": "facil",
            "opcoes": {
              "a": {
                "texto": "TEXTO ALTERNATIVA A",
                "correta": true
              },
              "b": {
                "texto": "TEXTO ALTERNATIVA B",
                "correta": false
              },
              "c": {
                "texto": "TEXTO ALTERNATIVA C",
                "correta": false
              },
              "d": {
                "texto": "TEXTO ALTERNATIVA D",
                "correta": false
              }
            }
          }
        }
      },
      "musicas": {
        "1": {
          "nomeMusica": "Nome da Música",
          "url": "link da música"
        },
        "2": {
          "nomeMusica": "Nome da Música",
          "url": "link da música"
        },
        "3": {
          "nomeMusica": "Nome da Música",
          "url": "link da música"
        },
        "4": {
          "nomeMusica": "Nome da Música",
          "url": "link da música"
        },
        "5": {
          "nomeMusica": "Nome da Música",
          "url": "link da música"
        },
        "6": {
          "nomeMusica": "Nome da Música",
          "url": "link da música"
        },
        "7": {
          "nomeMusica": "Nome da Música",
          "url": "link da música"
        },
        "8": {
          "nomeMusica": "Nome da Música",
          "url": "link da música"
        },
        "9": {
          "nomeMusica": "Nome da Música",
          "url": "link da música"
        },
        "10": {
          "nomeMusica": "Nome da Música",
          "url": "link da música"
        },
        "11": {
          "nomeMusica": "Nome da Música",
          "url": "link da música"
        },
        "12": {
          "nomeMusica": "Nome da Música",
          "url": "link da música"
        }
      },
      "frases": {
        "jogador1": {
          "1": {
          },
          "2": {
          },
          "3": {
          }
        },
        "jogador2": {
          "1": {
          },
          "2": {
          },
          "3": {
          }
        }
      }
    }
  }
}